{
  "persons": [
    {
      "name": "Arto Hellas",
      "number": "040-9876543",
      "id": 1
    },
    {
      "name": "Ada Lovelace",
      "number": "39-44-5323523",
      "id": 2
    },
    {
      "name": "Dan Abramov",
      "number": "12-43-234345",
      "id": 3
    },
    {
      "name": "Dwight Schrute",
      "number": "010-1239872",
      "id": 6
    },
    {
      "name": "Ron Swanson",
      "number": "123-1231233",
      "id": 8
    },
    {
      "name": "Michael Scott",
      "number": "456-12323434",
      "id": 9
    },
    {
      "name": "Elvis Presley",
      "number": "000-10101923",
      "id": 11
    }
  ]
}